inferbench/__init__.py
inferbench-0.0.1.dist-info/licenses/LICENSE
inferbench-0.0.1.dist-info/METADATA
inferbench-0.0.1.dist-info/WHEEL
inferbench-0.0.1.dist-info/top_level.txt
inferbench-0.0.1.dist-info/RECORD
