Metadata-Version: 2.4
Name: inferbench
Version: 0.0.1
Summary: A Python package for inference benchmarking
Author-email: Dan Mihailescu <dan.mihailescu@keysight.com>
License: MIT
Project-URL: Homepage, https://github.com/inferbench/inferbench
Project-URL: Repository, https://github.com/inferbench/inferbench
Classifier: Development Status :: 2 - Pre-Alpha
Classifier: Intended Audience :: Developers
Classifier: License :: OSI Approved :: MIT License
Classifier: Programming Language :: Python :: 3
Classifier: Programming Language :: Python :: 3.8
Classifier: Programming Language :: Python :: 3.9
Classifier: Programming Language :: Python :: 3.10
Classifier: Programming Language :: Python :: 3.11
Classifier: Programming Language :: Python :: 3.12
Requires-Python: >=3.8
License-File: LICENSE
Dynamic: license-file
